autothreats/__init__.py
autothreats/db.py
autothreats/message_types.py
autothreats/setup.py
autothreats/simplified_api_server.py
autothreats/simplified_base.py
autothreats/simplified_commit_analyzer.py
autothreats/simplified_container_runner.py
autothreats/simplified_orchestrator.py
autothreats/simplified_system_additions.py
autothreats/simplified_workspace.py
autothreats/ultra_simplified_agent_decorators.py
autothreats/agentic/__init__.py
autothreats/agentic/adaptive_prioritization.py
autothreats/agentic/agent_extension.py
autothreats/agentic/agent_integration.py
autothreats/agentic/agent_learning.py
autothreats/agentic/agent_monitor.py
autothreats/agentic/base_agent.py
autothreats/agentic/causal_reasoning.py
autothreats/agentic/collaborative_reasoning.py
autothreats/agentic/context_aware_analysis.py
autothreats/agentic/context_aware_security.py
autothreats/agentic/continuous_learning.py
autothreats/agentic/explainable_security.py
autothreats/agentic/hierarchical_analysis.py
autothreats/agentic/integration.py
autothreats/agentic/knowledge_sharing.py
autothreats/agentic/mcp_integration.py
autothreats/agentic/multi_agent_planning.py
autothreats/agentic/multi_stage_agent.py
autothreats/agentic/multi_stage_integration.py
autothreats/agentic/simplified_adaptive_prioritization.py
autothreats/agentic/simplified_agent_integration.py
autothreats/agentic/simplified_base_agent.py
autothreats/agentic/simplified_context_aware_security.py
autothreats/agentic/simplified_explainable_security.py
autothreats/agentic/simplified_hierarchical_analysis.py
autothreats/agentic/simplified_multi_stage_orchestrator.py
autothreats/agentic/threat_detection_agent.py
autothreats/agents/__init__.py
autothreats/agents/decorator_agent_registry.py
autothreats/agents/decorator_code_ingestion.py
autothreats/agents/decorator_language_id.py
autothreats/agents/decorator_normalization.py
autothreats/agents/decorator_risk_scoring.py
autothreats/agents/decorator_threat_detection.py
autothreats-0.1.3.dist-info/METADATA
autothreats-0.1.3.dist-info/WHEEL
autothreats-0.1.3.dist-info/entry_points.txt
autothreats-0.1.3.dist-info/top_level.txt
autothreats-0.1.3.dist-info/RECORD
